contacted/__init__.py
contacted/client.py
contacted/validation.py
contacted-0.0.12.dist-info/METADATA
contacted-0.0.12.dist-info/WHEEL
contacted-0.0.12.dist-info/top_level.txt
contacted-0.0.12.dist-info/RECORD
