Metadata-Version: 2.4
Name: contacted
Version: 0.0.12
Summary: Python SDK for Contacted email API service
Home-page: https://github.com/LawrenceGB/contacted-python
Author: Your Name
Author-email: ContactedAI <lawrence@contacted.io>
License: MIT
Project-URL: Homepage, https://contacted.io
Project-URL: Documentation, https://contacted.gitbook.io
Project-URL: Repository, https://github.com/LawrenceGB/contacted-python
Keywords: email,api,contacted,transactional-email
Classifier: Development Status :: 1 - Planning
Classifier: Intended Audience :: Developers
Classifier: License :: OSI Approved :: MIT License
Classifier: Programming Language :: Python :: 3
Classifier: Programming Language :: Python :: 3.7
Classifier: Programming Language :: Python :: 3.8
Classifier: Programming Language :: Python :: 3.9
Classifier: Programming Language :: Python :: 3.10
Classifier: Programming Language :: Python :: 3.11
Requires-Python: >=3.7
Dynamic: author
Dynamic: home-page
Dynamic: requires-python
